solution_efe_database/__init__.py
solution_efe_database/database.py
solution_efe_database-1.0.1.dist-info/METADATA
solution_efe_database-1.0.1.dist-info/WHEEL
solution_efe_database-1.0.1.dist-info/top_level.txt
solution_efe_database-1.0.1.dist-info/RECORD
