Metadata-Version: 2.1
Name: solution-efe-database
Version: 1.0.1
Summary: Paquete de base de datos
Home-page: UNKNOWN
Author: Rulman Ferro
Author-email: rulman26@gmail.com
License: MIT
Platform: UNKNOWN
Requires-Python: >=3.6
Requires-Dist: PyMySQL
Requires-Dist: solution-efe-config
